table_evaluator/__init__.py
table_evaluator/association_metrics.py
table_evaluator/metrics.py
table_evaluator/notebook.py
table_evaluator/plots.py
table_evaluator/table_evaluator.py
table_evaluator/types.py
table_evaluator/utils.py
table_evaluator/backends/__init__.py
table_evaluator/backends/backend_context.py
table_evaluator/backends/backend_factory.py
table_evaluator/backends/backend_manager.py
table_evaluator/backends/backend_types.py
table_evaluator/backends/base_backend.py
table_evaluator/backends/conversion_bridge.py
table_evaluator/backends/data_bridge.py
table_evaluator/backends/dataframe_wrapper.py
table_evaluator/backends/dtype_bridge.py
table_evaluator/backends/feature_flags.py
table_evaluator/backends/lazy_conversion.py
table_evaluator/backends/pandas_backend.py
table_evaluator/backends/polars_backend.py
table_evaluator/backends/schema_validator.py
table_evaluator/core/__init__.py
table_evaluator/core/evaluation_config.py
table_evaluator/data/__init__.py
table_evaluator/data/data_converter.py
table_evaluator/evaluators/__init__.py
table_evaluator/evaluators/ml_evaluator.py
table_evaluator/evaluators/privacy_evaluator.py
table_evaluator/evaluators/statistical_evaluator.py
table_evaluator/visualization/__init__.py
table_evaluator/visualization/layout_utils.py
table_evaluator/visualization/visualization_manager.py
table_evaluator-1.9.0.dist-info/licenses/LICENSE
table_evaluator-1.9.0.dist-info/METADATA
table_evaluator-1.9.0.dist-info/WHEEL
table_evaluator-1.9.0.dist-info/top_level.txt
table_evaluator-1.9.0.dist-info/RECORD
