Metadata-Version: 2.4
Name: table-evaluator
Version: 1.9.0
Summary: A package to evaluate how close a synthetic data set is to real data.
Author-email: Bauke Brenninkmeijer <bauke.brenninkmeijer@gmail.com>
License-Expression: MIT
Project-URL: Homepage, https://github.com/Baukebrenninkmeijer/Table-Evaluator
Project-URL: Documentation, https://baukebrenninkmeijer.github.io/table-evaluator/index.html
Keywords: Table-evaluation,synthetic-data,data-generation,data,generation,data-evaluation
Classifier: Programming Language :: Python
Classifier: Programming Language :: Python :: 3.10
Classifier: Programming Language :: Python :: 3.11
Classifier: Programming Language :: Python :: 3.12
Classifier: Programming Language :: Python :: 3 :: Only
Classifier: Operating System :: OS Independent
Requires-Python: >=3.10
License-File: LICENSE
Requires-Dist: pyarrow==17.0.0
Requires-Dist: scikit-learn==1.5.1
Requires-Dist: tqdm==4.66.5
Requires-Dist: matplotlib==3.9.2
Requires-Dist: numpy==1.26.4
Requires-Dist: seaborn==0.13.2
Requires-Dist: pandas==2.2.2
Requires-Dist: scipy==1.12.0
Requires-Dist: pre-commit==3.8.0
Requires-Dist: ipython==8.28.0
Requires-Dist: pytest==8.3.2
Requires-Dist: sphinx==7.3.1
Requires-Dist: pytest-cov==4.0.0
Requires-Dist: pytest-mock==3.14.0
Requires-Dist: m2r2==0.3.3.post2
Requires-Dist: setuptools
Requires-Dist: sphinx-rtd-theme==2.0.0
Requires-Dist: tomli>=1.2.0; python_version < "3.11"
Provides-Extra: dev
Requires-Dist: build>=1.2.2.post1; extra == "dev"
Requires-Dist: ipykernel>=6.29.5; extra == "dev"
Requires-Dist: ipywidgets>=8.1.7; extra == "dev"
Requires-Dist: psutil>=5.9.0; extra == "dev"
Requires-Dist: pytest-benchmark>=4.0.0; extra == "dev"
Provides-Extra: polars
Requires-Dist: polars<2.0.0,>=0.20.0; extra == "polars"
Provides-Extra: all
Requires-Dist: polars<2.0.0,>=0.20.0; extra == "all"
Requires-Dist: build>=1.2.2.post1; extra == "all"
Requires-Dist: ipykernel>=6.29.5; extra == "all"
Requires-Dist: ipywidgets>=8.1.7; extra == "all"
Requires-Dist: psutil>=5.9.0; extra == "all"
Requires-Dist: pytest-benchmark>=4.0.0; extra == "all"
Dynamic: license-file
